{"skeleton":{"hash":"kNsWEk+Kp/1ACaNnCVNPQWHXqMA","spine":"3.8.95","x":-257.44,"y":-844.41,"width":1597.1,"height":1742.77,"images":"./Tom4/","audio":"C:/Users/Zagado4naya Mol/Google Drive/джем0/Том в работе"},"bones":[{"name":"root"},{"name":"all1","parent":"root","x":-664.52,"y":5.42},{"name":"bone4","parent":"all1","x":-32.65},{"name":"Tom0","parent":"bone4","x":747.02,"y":79.17,"color":"fd0606ff"},{"name":"Tom","parent":"Tom0","rotation":0.07,"x":-13.04,"y":-8.08,"color":"fd0909ff"},{"name":"pelvis","parent":"Tom","length":77.9,"rotation":-81.1,"x":-28.87,"y":34.09},{"name":"hip_left","parent":"pelvis","length":402.51,"rotation":3.19,"x":62.01,"y":46.5},{"name":"shin_left","parent":"hip_left","length":356.41,"rotation":-8.05,"x":402.82,"y":-0.37},{"name":"foot_left","parent":"shin_left","length":116.74,"rotation":57.83,"x":340.11,"y":-12.01},{"name":"toes_left","parent":"foot_left","length":62.87,"rotation":23.41,"x":116.22,"y":0.3},{"name":"hip_right","parent":"pelvis","length":416.07,"rotation":-21.7,"x":60.75,"y":-13.43},{"name":"shin_right","parent":"hip_right","length":385.55,"rotation":-4.69,"x":414.75,"y":0.3},{"name":"foor_right","parent":"shin_right","length":114.41,"rotation":66.78,"x":387.14,"y":-31.61},{"name":"toes_right","parent":"foor_right","length":58.07,"rotation":21.3,"x":114.65,"y":0.47},{"name":"body2","parent":"Tom","length":171.9,"rotation":96.17,"x":7.43,"y":30.72},{"name":"body4","parent":"body2","length":282,"rotation":-3.77,"x":180.72,"y":-1.82},{"name":"neck","parent":"body4","length":73.44,"rotation":-1.83,"x":339.16,"y":5.04},{"name":"head","parent":"neck","length":97.54,"rotation":2.41,"x":86.46,"y":13.79},{"name":"body5","parent":"body4","length":132.45,"rotation":104.13,"x":284.79,"y":30.07},{"name":"shoulder_right","parent":"body5","length":332.55,"rotation":60.73,"x":135.56,"y":2.04},{"name":"forearm_right","parent":"shoulder_right","length":244.89,"rotation":33.65,"x":333.9,"y":-5.17},{"name":"palm_right","parent":"forearm_right","length":81.34,"rotation":5.75,"x":246.57,"y":0.87},{"name":"body6","parent":"body4","length":132.29,"rotation":-99.28,"x":286.5,"y":17.18},{"name":"shoulder_left","parent":"body6","length":313.85,"rotation":-78.83,"x":150.31,"y":2.16},{"name":"forearm_left","parent":"shoulder_left","length":241.38,"rotation":34.72,"x":309.99,"y":23.22},{"name":"palm_left","parent":"forearm_left","length":59.84,"rotation":-2.08,"x":237.26,"y":-20.93},{"name":"l_left","parent":"bone4","x":788.59,"y":-710.53,"color":"ff3f00ff"},{"name":"l_right","parent":"bone4","x":567.47,"y":-752.84,"color":"ff3f00ff"}],"slots":[{"name":"fingers_left","bone":"palm_left","attachment":"fingers_left"},{"name":"thumb_left","bone":"palm_left","attachment":"thumb_left"},{"name":"palm_left","bone":"palm_left","attachment":"palm_left"},{"name":"shadow_palm_left","bone":"forearm_left","attachment":"shadow_palm_left"},{"name":"forearm_left","bone":"forearm_left","attachment":"forearm_left"},{"name":"shoulder_left","bone":"shoulder_left","attachment":"shoulder_left"},{"name":"foot_left","bone":"foot_left","attachment":"foot_left"},{"name":"toes_left","bone":"toes_left","attachment":"toes_left"},{"name":"shin_left","bone":"shin_left","attachment":"shin_left"},{"name":"hip_left","bone":"hip_left","attachment":"hip_left"},{"name":"fold_left_clothes","bone":"hip_left","attachment":"fold_left_clothes"},{"name":"pelvis","bone":"pelvis","attachment":"pelvis"},{"name":"foot_right","bone":"foor_right","attachment":"foot_right"},{"name":"toes_right","bone":"toes_right","attachment":"toes_right"},{"name":"shin_right","bone":"shin_right","attachment":"shin_right"},{"name":"hip_right","bone":"hip_right","attachment":"hip_right"},{"name":"fold_leg_clothes","bone":"hip_right","attachment":"fold_leg_clothes"},{"name":"shadow-hip-pelvis","bone":"body2","attachment":"shadow-hip-pelvis"},{"name":"collar_back","bone":"body4","attachment":"collar_back"},{"name":"body2","bone":"body2","attachment":"body2"},{"name":"neck","bone":"neck","attachment":"neck"},{"name":"body3","bone":"body4","attachment":"body3"},{"name":"jacket left","bone":"body6","attachment":"jacket left"},{"name":"jacket_right","bone":"body5","attachment":"jacket_right"},{"name":"head","bone":"head","attachment":"head"},{"name":"eyes_1","bone":"head","attachment":"eyes_1"},{"name":"brows_1","bone":"head","attachment":"brows_1"},{"name":"mouth_1","bone":"head","attachment":"mouth_1-4"},{"name":"box_active","bone":"root"},{"name":"fingers_right","bone":"palm_right","attachment":"fingers_right"},{"name":"thumb_right","bone":"palm_right","attachment":"thumb_right"},{"name":"palm_right","bone":"palm_right","attachment":"palm_right"},{"name":"shadow_palm_right","bone":"forearm_right","attachment":"shadow_palm_right"},{"name":"forearm_right","bone":"forearm_right","attachment":"forearm_right"},{"name":"shoulder_right_clothes_noseam","bone":"shoulder_right","attachment":"shoulder_right_clothes_noseam"},{"name":"shoulder_right","bone":"shoulder_right","attachment":"shoulder_right"},{"name":"fold_arm_2","bone":"shoulder_right","attachment":"fold_arm_2"}],"ik":[{"name":"l_left","bones":["hip_left","shin_left"],"target":"l_left","bendPositive":false},{"name":"l_right","order":1,"bones":["hip_right","shin_right"],"target":"l_right","bendPositive":false}],"skins":[{"name":"default","attachments":{"body2":{"body2":{"x":195.09,"y":-22.01,"rotation":-96.24,"width":241,"height":465}},"body3":{"body3":{"type":"mesh","uvs":[1,0.10782,1,0.20249,0.97522,0.32285,0.94057,0.49109,0.90403,0.66855,0.86783,0.84436,0.64909,0.9149,0.38804,0.89848,0.28404,0.84411,0.22554,0.71678,0.13831,0.52694,0.05684,0.34964,0,0.22593,0.0325,0.14063,0.38136,0.02351,0.53012,0.02506,0.6827,0.02666,0.61898,0.68964,0.59662,0.52243,0.57229,0.34048,0.55522,0.21282],"triangles":[5,17,4,7,8,17,6,7,17,5,6,17,8,9,17,20,15,16,19,20,2,11,20,19,18,19,3,10,19,18,4,18,3,17,18,4,9,10,18,9,18,17,20,14,15,20,16,0,1,20,0,2,20,1,3,19,2,10,11,19,20,12,13,11,12,20,14,20,13],"vertices":[1,22,169.64,34.66,1,2,22,174.9,-11.05,0.95605,15,247.4,-153.65,0.04395,2,22,173.49,-70.1,0.84342,15,189.36,-142.74,0.15658,2,22,171.51,-152.63,0.88182,15,108.23,-127.48,0.11818,3,22,169.42,-239.68,0.33259,15,22.65,-111.39,0.42408,14,196.47,-114.39,0.24333,3,22,167.36,-325.93,0.144,15,-62.14,-95.45,0.23283,14,112.82,-93.26,0.62317,1,14,86.57,-18,1,3,18,121.67,346.5,0.12,15,-80.94,63.47,0.11968,14,103.84,66.51,0.76032,3,18,146.76,311.3,0.2,15,-52.92,96.4,0.2112,14,133.83,97.65,0.5888,3,18,147.25,246.5,0.41161,15,9.8,112.69,0.39154,14,197.43,110.06,0.19685,2,18,147.99,149.87,0.83278,15,103.32,136.99,0.16722,2,18,148.67,59.64,0.92483,15,190.66,159.69,0.07517,2,18,149.15,-3.33,0.99735,15,251.6,175.52,0.00265,1,18,126.9,-39.91,1,2,18,0.56,-61.13,0.512,15,343.93,45.54,0.488,3,18,-46.07,-46.22,0.144,22,11.47,56.94,0.13011,15,340.86,-3.32,0.72589,2,22,61.43,61.91,0.448,15,337.7,-53.42,0.552,3,22,77.43,-260.58,2.6E-4,15,16.85,-17.23,0.49574,14,196.47,-20.05,0.504,2,22,60.83,-180.69,0.0058,15,98.37,-13.73,0.9942,2,22,42.77,-93.76,0.02371,15,187.08,-9.92,0.97629,1,15,249.32,-7.25,1],"hull":17,"edges":[0,32,0,2,10,12,12,14,14,16,26,28,28,30,30,32,8,10,12,34,8,34,16,18,34,18,6,8,36,34,6,36,18,20,36,20,2,4,4,6,38,36,4,38,20,22,22,24,38,22,30,40,40,38,2,40,24,40,0,40,24,26],"width":329,"height":486}},"brows_1":{"brows_1":{"x":70.46,"y":-73.14,"rotation":-93.29,"width":90,"height":25},"brows_1-4":{"x":70.46,"y":-73.14,"rotation":-93.29,"width":90,"height":25},"brows_2":{"x":70.46,"y":-73.14,"rotation":-93.29,"width":88,"height":24},"brows_2-3":{"x":70.46,"y":-73.14,"rotation":-93.29,"width":88,"height":24}},"collar_back":{"collar_back":{"type":"mesh","uvs":[1,1,0.60226,1,0.39886,1,0,1,0,0.38773,0.38689,0,0.59628,0,1,0],"triangles":[1,7,0,2,3,4,2,6,1,2,4,5,2,5,6,1,6,7],"vertices":[2,15,314.91,-89.78,0.448,22,100.98,45.28,0.552,2,15,318.13,-21.84,0.92,22,33.41,37.51,0.08,2,15,319.78,12.9,0.888,18,-25.19,-29.74,0.112,2,15,323.01,81.03,0.56,18,40.09,-49.51,0.44,2,15,356.65,79.44,0.56,18,30.33,-81.74,0.44,2,15,374.82,12.34,0.888,18,-39.17,-82.98,0.112,2,15,373.12,-23.42,0.92,22,26.11,92.03,0.08,2,15,369.85,-92.38,0.448,22,94.69,99.92,0.552],"hull":8,"edges":[0,14,6,8,4,6,10,4,10,12,12,14,0,2,2,4,12,2,8,10],"width":171,"height":55}},"eyes_1":{"eyes_1":{"x":55.93,"y":-73.3,"rotation":-93.29,"width":80,"height":20},"eyes_2":{"x":57.22,"y":-76.88,"rotation":-93.29,"width":79,"height":21},"eyes_3":{"x":56.81,"y":-75.36,"rotation":-93.29,"width":82,"height":22},"eyes_4":{"x":53.31,"y":-75.16,"rotation":-93.29,"width":80,"height":17}},"fingers_left":{"fingers_left":{"x":92.2,"y":-24.4,"rotation":51.52,"width":66,"height":116}},"fingers_right":{"fingers_right":{"x":75.86,"y":13.88,"rotation":67.2,"width":106,"height":176}},"fold_arm_2":{"fold_arm_2":{"x":300.6,"y":15.98,"rotation":102.42,"width":67,"height":30}},"fold_left_clothes":{"fold_left_clothes":{"x":406.42,"y":-0.3,"rotation":83.94,"width":104,"height":53}},"fold_leg_clothes":{"fold_leg_clothes":{"x":435.6,"y":0.4,"rotation":97.85,"width":111,"height":52}},"foot_left":{"foot_left":{"x":63.09,"y":3.07,"rotation":35.13,"width":161,"height":137}},"foot_right":{"foot_right":{"x":67.4,"y":12.78,"rotation":38.13,"width":165,"height":143}},"forearm_left":{"forearm_left":{"x":113.5,"y":-15.37,"rotation":49.44,"width":219,"height":256}},"forearm_right":{"forearm_right":{"x":121.83,"y":10.04,"rotation":72.95,"width":152,"height":323}},"head":{"head":{"x":45.63,"y":-34.65,"rotation":-93.29,"width":212,"height":277}},"hip_left":{"hip_left":{"x":179.2,"y":0.2,"rotation":83.94,"width":135,"height":507}},"hip_right":{"hip_right":{"x":193.4,"y":14.57,"rotation":97.85,"width":166,"height":506}},"jacket_right":{"jacket_right":{"type":"mesh","uvs":[0,0.12534,0.5671,0.0126,0.63048,0,0.98799,0.00498,0.98954,0.11939,0.99165,0.2751,0.99492,0.51741,0.99815,0.75588,0.89104,1,0.73219,1,0.36955,0.99309,0.2107,0.95719,0.33079,0.63802,0.32439,0.54585,0.16254,0.34177,0.56743,0.04516],"triangles":[11,12,7,7,9,11,8,9,7,12,6,7,9,10,11,15,1,2,15,2,3,15,3,4,4,5,15,6,14,5,14,6,13,12,13,6,0,1,15,5,14,0,15,5,0],"vertices":[2,18,145.6,-39.19,0.976,15,287.25,180.84,0.024,2,18,36.62,-74.28,0.416,15,347.88,83.72,0.584,2,18,24.44,-78.21,0.44,15,354.66,72.87,0.56,2,18,-31.52,-58.25,0.088,15,348.97,13.72,0.912,2,18,-12.61,5.11,0.24,15,282.9,16.6,0.76,3,18,13.14,91.35,0.0553,15,192.99,20.51,0.8087,14,374.6,6.77,0.136,3,18,53.2,225.56,0.04198,15,53.06,26.59,0.61402,14,235.32,21.46,0.344,3,18,92.62,357.64,0.02598,15,-84.64,32.58,0.20602,14,98.24,35.91,0.768,2,18,150.53,487.53,0.128,14,-40.09,68.93,0.872,2,18,175.77,479.89,0.224,14,-37.22,95.14,0.776,2,18,232.22,458.62,0.248,14,-26.71,154.55,0.752,2,18,251.45,431.12,0.368,14,-3.21,178.5,0.632,3,18,178.91,260.33,0.78707,15,-11.35,140.02,0.05171,14,178.01,138.63,0.16122,3,18,164.49,209.04,0.75639,15,41.92,138.56,0.13123,14,231.08,133.89,0.11238,2,18,156.03,88.35,0.816,15,161.01,159.81,0.184,2,18,42.02,-56.25,0.456,15,329.08,84.56,0.544],"hull":15,"edges":[4,6,14,16,16,18,18,20,20,22,22,24,24,26,0,2,2,4,2,30,6,8,8,10,10,12,12,14,26,28,28,0],"width":166,"height":578}},"jacket left":{"jacket left":{"type":"mesh","uvs":[0.41211,1.0E-5,0.45736,0.00695,0.85274,0.08133,1,0.09269,0.99436,0.14383,0.93431,0.30077,0.89916,0.39266,0.86215,0.48938,0.81045,0.62452,0.72854,0.66286,0.83738,0.74827,0.95123,0.83761,0.91753,0.9507,0.73363,0.99214,0.46586,1,0.40036,0.87453,0.35561,0.78881,0.29989,0.68207,0.22572,0.54,0.1802,0.43786,0.14241,0.35306,0.06393,0.17695,0.02138,0.08148,0,0.02091,0.4863,0.04448],"triangles":[4,2,3,21,2,4,5,21,4,10,17,9,9,18,8,8,18,7,7,19,6,6,20,5,17,18,9,18,19,7,19,20,6,20,21,5,21,24,2,1,24,0,23,0,24,22,24,21,24,22,23,1,2,24,10,16,17,13,15,12,12,15,11,14,15,13,16,10,11,15,16,11],"vertices":[2,15,354.34,-81.56,0.824,22,86.52,82.87,0.176,2,15,350.12,-87.84,0.824,22,93.4,79.71,0.176,2,15,305.47,-142.33,0.096,22,154.37,44.43,0.904,1,22,176.02,40.46,1,2,15,269.23,-160.89,0.088,22,178.52,11.66,0.912,2,15,181.07,-148.11,0.328,22,180.13,-77.42,0.672,2,15,129.45,-140.63,0.328,22,181.07,-129.57,0.672,3,14,253.45,-135.89,0.05088,15,75.11,-132.76,0.37312,22,182.05,-184.46,0.576,3,14,177.74,-123.54,0.15942,15,-0.81,-121.76,0.26458,22,183.44,-261.16,0.576,3,14,156.89,-110.45,0.1895,15,-21.89,-109.03,0.3145,22,174.28,-284.02,0.496,3,14,107.72,-122.84,0.35942,15,-70.83,-122.3,0.21658,22,195.25,-330.18,0.424,2,14,56.29,-135.8,0.68,15,-122.02,-136.17,0.32,2,14,-7.16,-126.83,0.728,15,-185.62,-128.33,0.272,2,14,-28.8,-99.06,0.72,15,-207.76,-100.95,0.28,2,14,-30.75,-60.56,0.712,15,-210.38,-62.49,0.288,2,14,40.61,-55.83,0.536,15,-139.13,-56.49,0.464,2,14,89.35,-52.6,0.472,15,-90.45,-52.4,0.528,3,14,150.05,-48.57,0.15232,15,-29.83,-47.29,0.79968,22,114.62,-301.81,0.048,3,14,230.84,-43.21,0.25133,15,50.85,-40.5,0.70067,22,94.91,-223.27,0.048,3,14,288.85,-40.48,0.09901,15,108.81,-36.73,0.85299,22,81.85,-166.69,0.048,2,15,156.92,-33.6,0.936,22,71,-119.71,0.064,2,15,256.84,-27.1,0.928,22,48.48,-22.14,0.072,2,15,311.01,-23.57,0.912,22,36.27,30.75,0.088,2,15,345.34,-22.14,0.912,22,29.32,64.4,0.088,2,15,328.74,-90.97,0.824,22,99.93,59.12,0.176],"hull":24,"edges":[4,6,6,8,16,18,22,24,24,26,0,2,2,4,48,2,46,0,8,42,42,44,44,46,34,36,18,34,14,16,36,14,40,42,8,10,40,10,28,30,22,30,26,28,18,20,20,22,30,32,32,34,20,32,10,12,12,14,36,38,38,40,12,38],"width":143,"height":565}},"mouth_1":{"mouth_1":{"x":-17,"y":-78.63,"rotation":-93.29,"width":41,"height":9},"mouth_1-4":{"x":-17,"y":-78.63,"rotation":-93.29,"width":41,"height":9},"mouth_2":{"x":-14.45,"y":-77.77,"rotation":-93.29,"width":43,"height":10},"mouth_3":{"x":-15.15,"y":-81.24,"rotation":-93.29,"width":44,"height":17}},"neck":{"neck":{"x":9.61,"y":-11.01,"rotation":-90.88,"width":108,"height":279}},"palm_left":{"palm_left":{"x":51.69,"y":-6.26,"rotation":51.52,"width":86,"height":144}},"palm_right":{"palm_right":{"x":54.21,"y":12.68,"rotation":67.2,"width":125,"height":171}},"pelvis":{"pelvis":{"x":37.33,"y":33.31,"rotation":81.03,"width":177,"height":152}},"shadow-hip-pelvis":{"shadow-hip-pelvis":{"x":-11.38,"y":0.31,"rotation":-96.24,"width":164,"height":110}},"shadow_palm_left":{"shadow_palm_left":{"x":243.93,"y":-14.46,"rotation":49.44,"width":40,"height":47}},"shadow_palm_right":{"shadow_palm_right":{"x":249.43,"y":4.91,"rotation":72.95,"width":61,"height":72}},"shin_left":{"shin_left":{"x":160.54,"y":2.93,"rotation":91.25,"width":86,"height":395}},"shin_right":{"shin_right":{"x":173.91,"y":2.26,"rotation":98.89,"width":142,"height":436}},"shoulder_left":{"shoulder_left":{"x":157.26,"y":-6.71,"rotation":82.38,"width":149,"height":393}},"shoulder_right":{"shoulder_right":{"x":153.89,"y":10.29,"rotation":102.42,"width":167,"height":399}},"shoulder_right_clothes_noseam":{"shoulder_right_clothes_noseam":{"x":153.08,"y":11.65,"rotation":102.42,"width":170,"height":400}},"thumb_left":{"thumb_left":{"x":47.85,"y":-25.56,"rotation":51.52,"width":47,"height":94}},"thumb_right":{"thumb_right":{"x":57.56,"y":40.02,"rotation":67.2,"width":78,"height":54}},"toes_left":{"toes_left":{"x":14.51,"y":-2.78,"rotation":11.72,"width":144,"height":76}},"toes_right":{"toes_right":{"x":29.12,"y":7.1,"rotation":16.83,"width":150,"height":80}}}}],"animations":{"idle":{"bones":{"l_right":{"translate":[{"x":21.39,"y":1.45}]},"l_left":{"translate":[{"x":-42,"y":-6}]},"toes_right":{"rotate":[{"angle":2.69}]},"foor_right":{"rotate":[{"angle":-5.79}]},"shin_right":{"rotate":[{"angle":4.73}]},"hip_right":{"rotate":[{"angle":3.15}]},"toes_left":{"rotate":[{"angle":1.33}]},"foot_left":{"rotate":[{"angle":3.85}]},"shin_left":{"rotate":[{"angle":7.99}]},"hip_left":{"rotate":[{"angle":-10.01}]},"pelvis":{"rotate":[{"angle":-9.73}]},"forearm_left":{"rotate":[{"angle":-26.24},{"time":0.4,"angle":-25.34},{"time":0.8,"angle":-26.24}]},"shoulder_left":{"rotate":[{},{"time":0.4,"angle":-1.16},{"time":0.8}]},"body6":{"translate":[{},{"time":0.4,"x":-0.51,"y":-3.1},{"time":0.8}]},"forearm_right":{"rotate":[{"angle":-21.6}]},"shoulder_right":{"rotate":[{"angle":4.29},{"time":0.4,"angle":4.49},{"time":0.8,"angle":4.29}]},"body5":{"translate":[{},{"time":0.4,"x":-0.33,"y":1.32},{"time":0.8}]},"body4":{"rotate":[{},{"time":0.4,"angle":1.77},{"time":0.8}],"translate":[{},{"time":0.4,"x":2.3,"y":0.48},{"time":0.8}]},"body2":{"rotate":[{},{"time":0.4,"angle":-1.17},{"time":0.8}]},"Tom0":{"translate":[{},{"time":0.4,"x":4.29},{"time":0.8}]}}},"jump_down_cycle":{"bones":{"toes_right":{"rotate":[{"angle":8.07}]},"foor_right":{"rotate":[{"angle":-43.09}]},"shin_right":{"rotate":[{"angle":-10.17}],"translate":[{"x":24.83,"y":1}]},"hip_right":{"rotate":[{"angle":36.69}],"translate":[{"x":1,"y":14.58}]},"toes_left":{"rotate":[{"angle":1.33}]},"foot_left":{"rotate":[{"angle":12.48}]},"shin_left":{"rotate":[{"angle":-67.64}]},"hip_left":{"rotate":[{"angle":36.63}]},"pelvis":{"rotate":[{"angle":-9.73}]},"head":{"rotate":[{"angle":15.2}]},"neck":{"rotate":[{"angle":-4.2}]},"forearm_left":{"rotate":[{"angle":-2.2}]},"shoulder_left":{"rotate":[{"angle":40.1}],"translate":[{"x":-19.02,"y":4.6}]},"forearm_right":{"rotate":[{"angle":-50.2}],"translate":[{"x":-2.51,"y":-8.45}]},"shoulder_right":{"rotate":[{"angle":-25.42}]},"body4":{"rotate":[{"angle":2.04}],"translate":[{"x":-13,"y":-1.08}]},"body2":{"rotate":[{"angle":-4.55}],"translate":[{"x":-4.16,"y":-10.99}]},"Tom":{"translate":[{"x":0.02,"y":215.49}]},"Tom0":{"translate":[{"x":-114.92}]},"l_right":{"translate":[{"x":128.1,"y":200.42}]},"l_left":{"translate":[{"x":-111.72,"y":369.47}],"shear":[{"time":0.0333}]}}},"jump_end":{"bones":{"toes_right":{"rotate":[{"angle":8.07,"curve":"stepped"},{"time":0.1333,"angle":8.07},{"time":0.2667,"angle":2.69}]},"foor_right":{"rotate":[{"angle":-43.09},{"time":0.1333,"angle":21.41},{"time":0.2667,"angle":21.03},{"time":0.4,"angle":-5.79}]},"shin_right":{"rotate":[{"angle":-10.17},{"time":0.2667,"angle":4.73}],"translate":[{"x":24.83,"y":1},{"time":0.2667}]},"hip_right":{"rotate":[{"angle":36.69},{"time":0.2667,"angle":3.15}],"translate":[{"x":1,"y":14.58},{"time":0.1333,"x":-4.47,"y":11.63},{"time":0.2667}]},"toes_left":{"rotate":[{"angle":1.33}]},"foot_left":{"rotate":[{"angle":12.48},{"time":0.1333,"angle":30.08},{"time":0.2667,"angle":34.23},{"time":0.4,"angle":3.85}]},"shin_left":{"rotate":[{"angle":-67.64},{"time":0.2667,"angle":7.99}]},"hip_left":{"rotate":[{"angle":36.63},{"time":0.2667,"angle":-10.01}]},"pelvis":{"rotate":[{"angle":-9.73}]},"head":{"rotate":[{"angle":15.2},{"time":0.2667}]},"neck":{"rotate":[{"angle":-4.2},{"time":0.2667}]},"forearm_left":{"rotate":[{"angle":-2.2},{"time":0.1333,"angle":11.55},{"time":0.2667,"angle":-26.24}]},"shoulder_left":{"rotate":[{"angle":40.1,"curve":0.381,"c2":0.55,"c3":0.742},{"time":0.1333,"angle":21.93},{"time":0.2667,"angle":20.06},{"time":0.4}],"translate":[{"x":-19.02,"y":4.6,"curve":0.351,"c2":0.4,"c3":0.757},{"time":0.4}]},"forearm_right":{"rotate":[{"angle":-50.2},{"time":0.1333,"angle":-1},{"time":0.2667,"angle":-8.22},{"time":0.4,"angle":-21.6}],"translate":[{"x":-2.51,"y":-8.45},{"time":0.1333}]},"shoulder_right":{"rotate":[{"angle":-25.42,"curve":0.629,"c2":0.01,"c3":0.75},{"time":0.3333,"angle":7.65},{"time":0.4,"angle":4.29}]},"body4":{"rotate":[{"angle":2.04},{"time":0.1333,"angle":-6.99},{"time":0.2667,"angle":-6.05},{"time":0.4}],"translate":[{"x":-13,"y":-1.08},{"time":0.1333,"x":-15.6,"y":-1.29},{"time":0.2667}]},"body2":{"rotate":[{"angle":-4.55},{"time":0.1333,"angle":-17.16},{"time":0.2667,"angle":-5.04},{"time":0.4}],"translate":[{"x":-4.16,"y":-10.99},{"time":0.1333,"x":-4.99,"y":-13.19},{"time":0.2667}]},"Tom":{"translate":[{"x":0.02,"y":215.49,"curve":0.341,"c2":0.33,"c3":0.672,"c4":0.68},{"time":0.1333,"x":0.04,"y":-186.36,"curve":0.25,"c3":0.75},{"time":0.4}]},"Tom0":{"translate":[{"x":-114.92},{"time":0.1333,"x":-106.92},{"time":0.2667,"x":-10},{"time":0.4}]},"l_right":{"translate":[{"x":128.1,"y":200.42},{"time":0.1333,"x":-26.7,"y":1.45},{"time":0.2667,"x":14.6,"y":-12.14},{"time":0.4,"x":21.39,"y":1.45}]},"l_left":{"translate":[{"x":-111.72,"y":369.47},{"time":0.1333,"x":-42,"y":-6},{"time":0.2667,"x":-52.19,"y":-7.12},{"time":0.4,"x":-42,"y":-6}]}}},"jump_start":{"bones":{"toes_right":{"rotate":[{"angle":2.69},{"time":0.1333,"angle":8.07}]},"foor_right":{"rotate":[{"angle":-5.79,"curve":0.095,"c2":0.34,"c3":0.75},{"time":0.1333,"angle":21.41,"curve":0.095,"c2":0.34,"c3":0.75},{"time":0.2667,"angle":-37.86}]},"shin_right":{"rotate":[{"angle":4.73},{"time":0.2667,"angle":-10.51}],"translate":[{},{"time":0.2667,"x":7.51,"y":0.29}]},"hip_right":{"rotate":[{"angle":3.15},{"time":0.2667,"angle":31.33}],"translate":[{},{"time":0.1333,"x":-4.47,"y":11.63},{"time":0.2667,"x":-2.28,"y":12.81}]},"toes_left":{"rotate":[{"angle":1.33}]},"foot_left":{"rotate":[{"angle":3.85,"curve":0,"c2":0.37,"c3":0.75},{"time":0.1333,"angle":30.08,"curve":0.095,"c2":0.34,"c3":0.75},{"time":0.2667,"angle":-22.3}]},"shin_left":{"rotate":[{"angle":7.99},{"time":0.2667,"angle":-92.67}]},"hip_left":{"rotate":[{"angle":-10.01},{"time":0.2667,"angle":53.74}]},"pelvis":{"rotate":[{"angle":-9.73}]},"head":{"rotate":[{},{"time":0.2667,"angle":22.1}]},"neck":{"rotate":[{},{"time":0.1333,"angle":9.76},{"time":0.2667,"angle":-0.62}]},"forearm_left":{"rotate":[{"angle":-26.24},{"time":0.1333,"angle":20.33},{"time":0.2667,"angle":10.79}]},"shoulder_left":{"rotate":[{},{"time":0.1333,"angle":11.15,"curve":0.25,"c3":0.75},{"time":0.2667,"angle":131.86}],"translate":[{},{"time":0.2667,"x":-17.5,"y":-2.4}]},"forearm_right":{"rotate":[{"angle":-21.6},{"time":0.2667,"angle":30.05}]},"shoulder_right":{"rotate":[{"angle":4.29,"curve":0.25,"c3":0.75},{"time":0.1333,"angle":16.25,"curve":0.25,"c3":0.75},{"time":0.2667,"angle":104.86}]},"body4":{"rotate":[{},{"time":0.1333,"angle":-14.72},{"time":0.2667,"angle":-2.47}],"translate":[{},{"time":0.2667,"x":-3.71,"y":-0.31}]},"body2":{"rotate":[{},{"time":0.1333,"angle":-21.01},{"time":0.2667,"angle":-27.31}],"translate":[{},{"time":0.2667,"x":-1.19,"y":-3.14}]},"Tom":{"translate":[{},{"time":0.1333,"y":-155.93,"curve":0.233,"c2":0.23,"c3":0.625,"c4":0.66},{"time":0.2667,"y":410.52}]},"Tom0":{"translate":[{},{"time":0.1333,"x":-146.92},{"time":0.2667,"x":-142.12}]},"l_right":{"translate":[{"x":21.39,"y":1.45},{"time":0.1333,"x":-26.7,"y":1.45},{"time":0.2667,"x":17.12,"y":409.73}]},"l_left":{"translate":[{"x":-42,"y":-6,"curve":"stepped"},{"time":0.1333,"x":-42,"y":-6},{"time":0.2667,"x":-95.5,"y":685.01}]}}},"jump_up_cycle":{"bones":{"toes_right":{"rotate":[{"angle":8.07}]},"foor_right":{"rotate":[{"angle":-37.86}]},"shin_right":{"rotate":[{"angle":-10.51}],"translate":[{"x":7.51,"y":0.29}]},"hip_right":{"rotate":[{"angle":31.33}],"translate":[{"x":-2.28,"y":12.81}]},"toes_left":{"rotate":[{"angle":1.33}]},"foot_left":{"rotate":[{"angle":-22.3}]},"shin_left":{"rotate":[{"angle":-92.67}]},"hip_left":{"rotate":[{"angle":53.74}]},"pelvis":{"rotate":[{"angle":-9.73}]},"head":{"rotate":[{"angle":22.1}]},"neck":{"rotate":[{"angle":-0.62}]},"forearm_left":{"rotate":[{"angle":10.79}]},"shoulder_left":{"rotate":[{"angle":131.86}],"translate":[{"x":-17.5,"y":-2.4}]},"forearm_right":{"rotate":[{"angle":30.05}]},"shoulder_right":{"rotate":[{"angle":104.86}]},"body4":{"rotate":[{"angle":-2.47}],"translate":[{"x":-3.71,"y":-0.31}]},"body2":{"rotate":[{"angle":-27.31}],"translate":[{"x":-1.19,"y":-3.14}]},"Tom":{"translate":[{"y":410.52}]},"Tom0":{"translate":[{"x":-142.12}]},"l_right":{"translate":[{"x":17.12,"y":409.73}]},"l_left":{"translate":[{"x":-95.5,"y":685.01}],"shear":[{"time":0.0333}]}}},"pull_cycle":{"bones":{"Tom0":{"translate":[{"x":-156.64}]},"Tom":{"translate":[{"x":0.26,"y":-222.5},{"time":0.2333,"x":0.29,"y":-248.12},{"time":0.4667,"x":0.26,"y":-222.5},{"time":0.7,"x":0.29,"y":-248.12},{"time":0.9333,"x":0.26,"y":-222.5}]},"body2":{"rotate":[{"angle":-49.76}],"translate":[{"x":-11.1,"y":-11.67}]},"body4":{"rotate":[{"angle":-10.92},{"time":0.2333,"angle":-7.19},{"time":0.4667,"angle":-10.92},{"time":0.7,"angle":-7.19},{"time":0.9333,"angle":-10.92}],"translate":[{"x":3.79,"y":-0.99}]},"body5":{"translate":[{"x":10.79,"y":-42.88}]},"shoulder_right":{"rotate":[{"angle":98.79}]},"forearm_right":{"rotate":[{"angle":20.17}]},"body6":{"translate":[{"x":10.06,"y":61.58}]},"shoulder_left":{"rotate":[{"angle":57.84}],"translate":[{"x":-30.15,"y":10.19}]},"forearm_left":{"rotate":[{"angle":60.75}]},"neck":{"rotate":[{"angle":14.91}]},"head":{"rotate":[{"angle":-5.81}]},"pelvis":{"rotate":[{"angle":-6.94}]},"hip_left":{"rotate":[{"angle":6.3}]},"shin_left":{"rotate":[{"angle":-75.41}]},"foot_left":{"rotate":[{"angle":26.73},{"time":0.2333,"angle":34.77},{"time":0.4667,"angle":5.67},{"time":0.9333,"angle":26.73}]},"toes_left":{"rotate":[{"angle":22.56},{"time":0.2333,"angle":11.26},{"time":0.4667,"angle":-2.99},{"time":0.7,"angle":5.7},{"time":0.9333,"angle":22.56}]},"hip_right":{"rotate":[{"angle":82.89}],"translate":[{"x":-1.67,"y":16.77}]},"shin_right":{"rotate":[{"angle":-53.9}]},"foor_right":{"rotate":[{"angle":-7.55},{"time":0.4667,"angle":13.32},{"time":0.7,"angle":6.35},{"time":0.9333,"angle":-7.55}]},"toes_right":{"rotate":[{"angle":5.74},{"time":0.4667,"angle":32.71},{"time":0.7,"angle":6.24},{"time":0.9333,"angle":5.74}]},"l_left":{"translate":[{"x":-449.95,"y":27.55},{"time":0.4667,"x":157.44,"y":-30,"curve":0.25,"c3":0.803,"c4":0.66},{"time":0.7,"x":106.32,"y":148.1,"curve":0.25,"c3":0.75},{"time":0.9333,"x":-449.95,"y":27.55}]},"l_right":{"translate":[{"x":388.17,"y":5.69},{"time":0.2333,"x":219.4,"y":87.21,"curve":0.25,"c3":0.75},{"time":0.4667,"x":-248.94,"y":40.26,"curve":0.25,"c3":0.803,"c4":0.66},{"time":0.7,"x":176.58,"y":28.74,"curve":0.25,"c3":0.75},{"time":0.9333,"x":388.17,"y":5.69}]}}},"pull_end":{"bones":{"Tom0":{"translate":[{"x":-156.64},{"time":0.1667,"x":-39.26},{"time":0.5}]},"Tom":{"translate":[{"x":0.26,"y":-222.5,"curve":"stepped"},{"time":0.1667,"x":0.26,"y":-222.5,"curve":0.192,"c2":0.23,"c3":0.75},{"time":0.5}]},"body2":{"rotate":[{"angle":-49.76},{"time":0.1667,"angle":-42.22},{"time":0.5}],"translate":[{"x":-11.1,"y":-11.67},{"time":0.5}]},"body4":{"rotate":[{"angle":-10.92},{"time":0.1667,"angle":-1.68},{"time":0.5}],"translate":[{"x":3.79,"y":-0.99},{"time":0.5}]},"body5":{"translate":[{"x":10.79,"y":-42.88},{"time":0.5}]},"shoulder_right":{"rotate":[{"angle":98.79},{"time":0.1667,"angle":83.83},{"time":0.5,"angle":4.29}]},"forearm_right":{"rotate":[{"angle":20.17},{"time":0.1667,"angle":11.19},{"time":0.5,"angle":-21.6}]},"body6":{"translate":[{"x":10.06,"y":61.58},{"time":0.5}]},"shoulder_left":{"rotate":[{"angle":57.84},{"time":0.1667,"angle":30.42},{"time":0.5}],"translate":[{"x":-30.15,"y":10.19},{"time":0.5}]},"forearm_left":{"rotate":[{"angle":60.75,"curve":"stepped"},{"time":0.1667,"angle":60.75},{"time":0.5,"angle":-26.24}]},"neck":{"rotate":[{"angle":14.91},{"time":0.5}]},"head":{"rotate":[{"angle":-5.81},{"time":0.5}]},"pelvis":{"rotate":[{"angle":-6.94},{"time":0.5,"angle":-9.73}]},"hip_left":{"rotate":[{"angle":6.3},{"time":0.5,"angle":-10.01}]},"shin_left":{"rotate":[{"angle":-75.41},{"time":0.5,"angle":7.99}]},"foot_left":{"rotate":[{"angle":26.73},{"time":0.5,"angle":3.85}]},"toes_left":{"rotate":[{"angle":22.56},{"time":0.5,"angle":1.33}]},"hip_right":{"rotate":[{"angle":82.89},{"time":0.5,"angle":3.15}],"translate":[{"time":0.1667,"x":-1.67,"y":16.77},{"time":0.5}]},"shin_right":{"rotate":[{"angle":-53.9},{"time":0.5,"angle":4.73}]},"foor_right":{"rotate":[{"angle":-7.55},{"time":0.1667,"angle":9.41},{"time":0.5,"angle":-5.79}]},"toes_right":{"rotate":[{"angle":5.74},{"time":0.5,"angle":2.69}]},"l_left":{"translate":[{"x":-449.95,"y":27.55},{"time":0.1667,"x":-329.95,"y":27.55,"curve":0.25,"c3":0.803,"c4":0.66},{"time":0.5,"x":-42,"y":-6}]},"l_right":{"translate":[{"x":388.17,"y":5.69,"curve":"stepped"},{"time":0.1667,"x":388.17,"y":5.69,"curve":0.192,"c2":0.23,"c3":0.75},{"time":0.5,"x":21.39,"y":1.45}]}}},"pull_start":{"bones":{"Tom0":{"translate":[{},{"time":0.2333,"x":2.18},{"time":0.4333,"x":-104.43},{"time":0.6667,"x":-156.64}]},"Tom":{"translate":[{},{"time":0.2333,"x":0.14,"y":-120},{"time":0.4333,"x":0.26,"y":-222.5},{"time":0.6667,"x":0.29,"y":-248.12},{"time":0.9,"x":0.26,"y":-222.5}]},"body2":{"rotate":[{},{"time":0.2333,"angle":-37.94},{"time":0.4333,"angle":-49.76}],"translate":[{},{"time":0.4333,"x":-11.1,"y":-11.67}]},"body4":{"rotate":[{},{"time":0.2333,"angle":-26.5},{"time":0.4333,"angle":-10.92},{"time":0.6667,"angle":-7.19},{"time":0.9,"angle":-10.92}],"translate":[{},{"time":0.4333,"x":3.79,"y":-0.99}]},"body5":{"translate":[{},{"time":0.2333,"x":10.79,"y":-42.88}]},"shoulder_right":{"rotate":[{"angle":4.29},{"time":0.2333,"angle":83.56},{"time":0.4333,"angle":98.79},{"time":0.6667,"angle":101.67},{"time":0.9,"angle":100.71}]},"forearm_right":{"rotate":[{"angle":-21.6},{"time":0.2333,"angle":25.77},{"time":0.4333,"angle":20.17},{"time":0.6667,"angle":15.76},{"time":0.9,"angle":17.23}]},"body6":{"translate":[{},{"time":0.2333,"x":10.06,"y":61.58}]},"shoulder_left":{"rotate":[{},{"time":0.2333,"angle":36.8},{"time":0.4333,"angle":57.84},{"time":0.6667,"angle":60.15},{"time":0.9,"angle":59.38}],"translate":[{},{"time":0.4333,"x":-30.15,"y":10.19}]},"forearm_left":{"rotate":[{"angle":-26.24},{"time":0.2333,"angle":72.01},{"time":0.4333,"angle":60.75}]},"neck":{"rotate":[{},{"time":0.2333,"angle":14.91}]},"head":{"rotate":[{},{"time":0.2333,"angle":4.61},{"time":0.4333,"angle":-5.81}]},"pelvis":{"rotate":[{"angle":-9.73},{"time":0.2333,"angle":-6.94}]},"hip_left":{"rotate":[{"angle":-10.01},{"time":0.4333,"angle":58.42},{"time":0.9,"angle":7.22}]},"shin_left":{"rotate":[{"angle":7.99},{"time":0.4333,"angle":-48.5},{"time":0.9,"angle":-79.97}]},"foot_left":{"rotate":[{"angle":3.85},{"time":0.4333,"angle":-8.15},{"time":0.9,"angle":26.73}]},"toes_left":{"rotate":[{"angle":1.33},{"time":0.4333,"angle":2.85},{"time":0.6667,"angle":5.7},{"time":0.9,"angle":22.56}]},"hip_right":{"rotate":[{"angle":3.15},{"time":0.4333,"angle":60.06},{"time":0.9,"angle":81.24}],"translate":[{},{"time":0.2333,"x":6.31,"y":8.91},{"time":0.4333,"x":-1.67,"y":16.77}]},"shin_right":{"rotate":[{"angle":4.73},{"time":0.4333,"angle":-88.68},{"time":0.9,"angle":-54.52}]},"foor_right":{"rotate":[{"angle":-5.79},{"time":0.2333,"angle":12.47},{"time":0.4333,"angle":15.39},{"time":0.6667,"angle":6.35},{"time":0.9,"angle":-7.55}]},"toes_right":{"rotate":[{"angle":2.69},{"time":0.2333,"angle":15.08},{"time":0.4333,"angle":17.55},{"time":0.6667,"angle":6.24},{"time":0.9,"angle":5.74}]},"l_left":{"translate":[{"x":-42,"y":-6},{"time":0.2333,"x":265.81,"curve":"stepped"},{"time":0.4333,"x":265.81,"curve":0.25,"c3":0.803,"c4":0.66},{"time":0.6667,"x":106.32,"y":148.1,"curve":0.25,"c3":0.75},{"time":0.9,"x":-449.95,"y":50.6}]},"l_right":{"translate":[{"x":21.39,"y":1.45},{"time":0.2333,"y":28.74,"curve":"stepped"},{"time":0.4333,"y":28.74,"curve":0.25,"c3":0.803,"c4":0.66},{"time":0.6667,"x":176.58,"y":28.74,"curve":0.25,"c3":0.75},{"time":0.9,"x":367.43,"y":-5.84}]}}},"push_cycle":{"bones":{"Tom0":{"translate":[{"x":-21.83}]},"Tom":{"translate":[{"x":0.28,"y":-233.18},{"time":0.2333,"x":0.29,"y":-248.12},{"time":0.4667,"x":0.26,"y":-222.5},{"time":0.7,"x":0.29,"y":-248.12},{"time":0.9333,"x":0.28,"y":-233.18}]},"body2":{"rotate":[{"angle":-60.21},{"time":0.4667,"angle":-54.93},{"time":0.9333,"angle":-60.21}],"translate":[{"x":11.35,"y":-24.53}]},"body4":{"rotate":[{"angle":3.98},{"time":0.4667,"angle":-4.69},{"time":0.9333,"angle":3.98}],"translate":[{"x":3.79,"y":-0.99}]},"body5":{"rotate":[{"angle":-0.08}],"translate":[{"x":10.79,"y":-42.88}]},"shoulder_right":{"rotate":[{"angle":61.6}],"translate":[{"x":-15.22,"y":12.65}]},"forearm_right":{"rotate":[{"angle":57.67}]},"body6":{"rotate":[{"angle":11.76}],"translate":[{"x":10.06,"y":61.58}]},"shoulder_left":{"rotate":[{"angle":5.22}],"translate":[{"x":6.33,"y":3.43}],"scale":[{"x":0.868}]},"forearm_left":{"rotate":[{"angle":86.22}],"scale":[{"x":0.909}]},"neck":{"rotate":[{"angle":14.91}]},"head":{"rotate":[{"angle":-5.81}]},"pelvis":{"rotate":[{"angle":-6.94}]},"hip_left":{"rotate":[{"angle":60.11}]},"shin_left":{"rotate":[{"angle":-64.33}]},"foot_left":{"rotate":[{"angle":1.03},{"time":0.2333,"angle":43.66},{"time":0.4667,"angle":17.09},{"time":0.7,"angle":10.19},{"time":0.9333,"angle":1.03}]},"toes_left":{"rotate":[{"angle":4.04},{"time":0.2333,"angle":5.7},{"time":0.4667,"angle":36.9},{"time":0.7,"angle":11.26},{"time":0.9333,"angle":4.04}]},"hip_right":{"rotate":[{"angle":-5.72}],"translate":[{"x":27.24,"y":-14.28},{"time":0.2333,"x":18.73,"y":27.75},{"time":0.4667,"x":4.01,"y":21.03},{"time":0.7,"x":0.99,"y":13.9},{"time":0.9333,"x":27.24,"y":-14.28}]},"shin_right":{"rotate":[{"angle":-48}]},"foor_right":{"rotate":[{"angle":8.36},{"time":0.2333,"angle":17.18},{"time":0.4667,"angle":-4.03},{"time":0.7,"angle":17.85},{"time":0.9333,"angle":8.36}]},"toes_right":{"rotate":[{"angle":35.77},{"time":0.2333,"angle":6.24},{"time":0.4667,"angle":5.74},{"time":0.9333,"angle":35.77}]},"l_left":{"translate":[{"x":265.81,"curve":0.25,"c3":0.803,"c4":0.66},{"time":0.2333,"x":-150.15,"y":25.32,"curve":0.192,"c2":0.23,"c3":0.75},{"time":0.4667,"x":-634.73,"y":57.87,"curve":0.372,"c3":0.803,"c4":0.66},{"time":0.7,"x":-198.28,"y":167.81,"curve":0.192,"c2":0.23,"c3":0.75},{"time":0.9333,"x":265.81}]},"l_right":{"translate":[{"x":-463.33,"y":81.45,"curve":0.25,"c3":0.803,"c4":0.66},{"time":0.2333,"x":-1.67,"y":276.76,"curve":0.192,"c2":0.23,"c3":0.75},{"time":0.4667,"x":460.88,"y":-16.74,"curve":0.25,"c3":0.803,"c4":0.66},{"time":0.7,"x":116.27,"y":6.67,"curve":0.192,"c2":0.23,"c3":0.75},{"time":0.9333,"x":-463.33,"y":81.45}]}}},"push_end":{"bones":{"Tom0":{"translate":[{"x":-21.83},{"time":0.1667,"x":-104.43},{"time":0.3333,"x":-39.26},{"time":0.6667}]},"Tom":{"translate":[{"x":0.28,"y":-233.18},{"time":0.1667,"x":0.26,"y":-222.5,"curve":"stepped"},{"time":0.3333,"x":0.26,"y":-222.5,"curve":0.192,"c2":0.23,"c3":0.75},{"time":0.6667}]},"body2":{"rotate":[{"angle":-60.21},{"time":0.1667,"angle":-49.76},{"time":0.3333,"angle":-42.22},{"time":0.6667}],"translate":[{"x":11.35,"y":-24.53},{"time":0.1667,"x":6.38,"y":-19.8},{"time":0.6667}]},"body4":{"rotate":[{"angle":3.98},{"time":0.1667,"angle":-10.92},{"time":0.3333,"angle":-1.68},{"time":0.6667}],"translate":[{"x":3.79,"y":-0.99,"curve":"stepped"},{"time":0.1667,"x":3.79,"y":-0.99},{"time":0.6667}]},"body5":{"rotate":[{"angle":-0.08,"curve":"stepped"},{"time":0.1667,"angle":-0.08},{"time":0.6667}],"translate":[{"x":10.79,"y":-42.88,"curve":"stepped"},{"time":0.1667,"x":10.79,"y":-42.88},{"time":0.6667}]},"shoulder_right":{"rotate":[{"angle":61.6},{"time":0.1667,"angle":81.05},{"time":0.3333,"angle":83.83},{"time":0.6667,"angle":4.29}],"translate":[{"x":-15.22,"y":12.65,"curve":"stepped"},{"time":0.1667,"x":-15.22,"y":12.65},{"time":0.6667}]},"forearm_right":{"rotate":[{"angle":57.67},{"time":0.1667,"angle":33.42},{"time":0.3333,"angle":11.19},{"time":0.6667,"angle":-21.6}]},"body6":{"rotate":[{"angle":11.76,"curve":"stepped"},{"time":0.1667,"angle":11.76},{"time":0.6667}],"translate":[{"x":10.06,"y":61.58,"curve":"stepped"},{"time":0.1667,"x":10.06,"y":61.58},{"time":0.6667}]},"shoulder_left":{"rotate":[{"angle":5.22},{"time":0.1667,"angle":41.46},{"time":0.3333,"angle":30.42},{"time":0.6667}],"translate":[{"x":6.33,"y":3.43,"curve":"stepped"},{"time":0.1667,"x":6.33,"y":3.43},{"time":0.6667}],"scale":[{"x":0.868,"curve":"stepped"},{"time":0.1667,"x":0.868},{"time":0.6667}]},"forearm_left":{"rotate":[{"angle":86.22},{"time":0.1667,"angle":81.23},{"time":0.3333,"angle":60.75},{"time":0.6667,"angle":-26.24}],"scale":[{"x":0.909},{"time":0.1667}]},"neck":{"rotate":[{"angle":14.91,"curve":"stepped"},{"time":0.1667,"angle":14.91},{"time":0.6667}]},"head":{"rotate":[{"angle":-5.81,"curve":"stepped"},{"time":0.1667,"angle":-5.81},{"time":0.6667}]},"pelvis":{"rotate":[{"angle":-6.94,"curve":"stepped"},{"time":0.1667,"angle":-6.94},{"time":0.6667,"angle":-9.73}]},"hip_left":{"rotate":[{"angle":60.11},{"time":0.1667,"angle":58.42},{"time":0.6667,"angle":-10.01}]},"shin_left":{"rotate":[{"angle":-64.33},{"time":0.1667,"angle":-48.5},{"time":0.6667,"angle":7.99}]},"foot_left":{"rotate":[{"angle":1.03},{"time":0.1667,"angle":-8.15},{"time":0.4333,"angle":13.1},{"time":0.6667,"angle":3.85}]},"toes_left":{"rotate":[{"angle":4.04},{"time":0.1667,"angle":2.85},{"time":0.6667,"angle":1.33}]},"hip_right":{"rotate":[{"angle":-5.72},{"time":0.1667,"angle":32.52},{"time":0.6667,"angle":3.15}],"translate":[{"x":27.24,"y":-14.28},{"time":0.1667,"x":-2.03,"y":6.77},{"time":0.3333,"x":-1.67,"y":16.77},{"time":0.6667}]},"shin_right":{"rotate":[{"angle":-48},{"time":0.1667,"angle":-79.22},{"time":0.6667,"angle":4.73}]},"foor_right":{"rotate":[{"angle":8.36},{"time":0.1667,"angle":15.39,"curve":0.192,"c2":0.23,"c3":0.75},{"time":0.6667,"angle":-5.79}]},"toes_right":{"rotate":[{"angle":35.77},{"time":0.1667,"angle":32.19},{"time":0.6667,"angle":2.69}]},"l_left":{"rotate":[{"time":0.1667},{"time":0.4333,"angle":-14.23},{"time":0.6667}],"translate":[{"x":265.81,"curve":"stepped"},{"time":0.1667,"x":265.81,"curve":0.313,"c3":0.647,"c4":0.34},{"time":0.6667,"x":-42,"y":-6}]},"l_right":{"translate":[{"x":-463.33,"y":81.45,"curve":0.25,"c3":0.803,"c4":0.66},{"time":0.1667,"x":-243.33,"y":47.19,"curve":0.252,"c3":0.622,"c4":0.48},{"time":0.4,"x":-132.38,"y":46.67,"curve":0.372,"c2":0.48,"c3":0.752},{"time":0.6667,"x":21.39,"y":1.45}]}}},"push_start":{"bones":{"Tom0":{"translate":[{},{"time":0.2333,"x":2.18},{"time":0.4333,"x":-104.43},{"time":0.6,"x":-21.83}]},"Tom":{"translate":[{},{"time":0.2333,"x":0.14,"y":-120},{"time":0.4333,"x":0.26,"y":-222.5},{"time":0.6,"x":0.28,"y":-233.18}]},"body2":{"rotate":[{},{"time":0.2333,"angle":-37.94},{"time":0.4333,"angle":-49.76},{"time":0.6,"angle":-60.21}],"translate":[{},{"time":0.4333,"x":11.35,"y":-24.53}]},"body4":{"rotate":[{},{"time":0.2333,"angle":-26.5},{"time":0.4333,"angle":-10.92},{"time":0.6,"angle":3.98}],"translate":[{},{"time":0.4333,"x":3.79,"y":-0.99}]},"body5":{"rotate":[{},{"time":0.4333,"angle":-0.08}],"translate":[{},{"time":0.2333,"x":10.79,"y":-42.88}]},"shoulder_right":{"rotate":[{"angle":4.29},{"time":0.2333,"angle":83.56},{"time":0.4333,"angle":81.05},{"time":0.6,"angle":61.6}],"translate":[{},{"time":0.4333,"x":-15.22,"y":12.65}]},"forearm_right":{"rotate":[{"angle":-21.6},{"time":0.2333,"angle":25.77},{"time":0.4333,"angle":39.79},{"time":0.6,"angle":57.67}]},"body6":{"rotate":[{},{"time":0.4333,"angle":11.76}],"translate":[{},{"time":0.2333,"x":10.06,"y":61.58}]},"shoulder_left":{"rotate":[{},{"time":0.2333,"angle":36.8},{"time":0.4333,"angle":25.89},{"time":0.6,"angle":5.22}],"translate":[{},{"time":0.4333,"x":6.33,"y":3.43}],"scale":[{},{"time":0.4333,"x":0.868}]},"forearm_left":{"rotate":[{"angle":-26.24},{"time":0.2333,"angle":72.01},{"time":0.4333,"angle":74.59},{"time":0.6,"angle":86.22}],"scale":[{},{"time":0.4333,"x":0.909}]},"neck":{"rotate":[{},{"time":0.2333,"angle":14.91}]},"head":{"rotate":[{},{"time":0.2333,"angle":4.61},{"time":0.4333,"angle":-5.81}]},"pelvis":{"rotate":[{"angle":-9.73},{"time":0.2333,"angle":-6.94}]},"hip_left":{"rotate":[{"angle":-1.55},{"time":0.4333,"angle":58.42},{"time":0.6,"angle":60.11}]},"shin_left":{"rotate":[{"angle":5.56},{"time":0.4333,"angle":-48.5},{"time":0.6,"angle":-64.33}]},"foot_left":{"rotate":[{"angle":3.85},{"time":0.4333,"angle":-8.15},{"time":0.6,"angle":1.03}]},"toes_left":{"rotate":[{"angle":1.33},{"time":0.4333,"angle":2.85},{"time":0.6,"angle":4.04}]},"hip_right":{"rotate":[{"angle":15.12},{"time":0.4333,"angle":60.06},{"time":0.6,"angle":-5.72}],"translate":[{},{"time":0.2333,"x":6.31,"y":8.91},{"time":0.4333,"x":-2.03,"y":6.77},{"time":0.6,"x":27.24,"y":-14.28}]},"shin_right":{"rotate":[{"angle":4.73},{"time":0.4333,"angle":-88.68},{"time":0.6,"angle":-48}]},"foor_right":{"rotate":[{"angle":-5.79},{"time":0.2333,"angle":12.47},{"time":0.4333,"angle":15.39},{"time":0.6,"angle":8.36}]},"toes_right":{"rotate":[{"angle":2.69},{"time":0.2333,"angle":15.08},{"time":0.4333,"angle":32.19},{"time":0.6,"angle":35.77}]},"l_left":{"translate":[{"x":-42,"y":-6},{"time":0.2333,"x":265.81}]},"l_right":{"translate":[{"x":21.39,"y":1.45},{"time":0.3333,"x":-243.33,"y":72.5,"curve":0.298,"c3":0.524},{"time":0.6,"x":-463.33,"y":81.45}]}}},"run_cycle":{"slots":{"shoulder_right":{"attachment":[{"name":null}]}},"bones":{"l_left":{"translate":[{"x":-153.69,"y":224.75},{"time":0.1,"x":-122.92,"y":320.04},{"time":0.2,"x":106.58,"y":271.4},{"time":0.3,"x":183.98,"y":11.73},{"time":0.4,"x":-83.62,"y":8.4},{"time":0.5,"x":-359.72,"y":84.31},{"time":0.6,"x":-506.42,"y":319.27},{"time":0.7,"x":-362.05,"y":272.1},{"time":0.8,"x":-153.69,"y":224.75}]},"toes_right":{"rotate":[{"angle":13.25},{"time":0.1,"angle":26.84},{"time":0.2,"angle":-2.6},{"time":0.4,"angle":-9.92},{"time":0.6,"angle":8.66},{"time":0.8,"angle":13.25}]},"foor_right":{"rotate":[{"angle":-1.13},{"time":0.1,"angle":-20.72},{"time":0.2,"angle":-27.03},{"time":0.4,"angle":-1.33},{"time":0.7,"angle":14.58},{"time":0.8,"angle":-1.13}]},"shin_right":{"rotate":[{"angle":-34.85}]},"hip_right":{"rotate":[{"angle":23.45}],"translate":[{},{"time":0.2,"x":-1.66,"y":-0.23},{"time":0.3,"x":-6.88,"y":1.61},{"time":0.4,"x":-10.8,"y":7.23,"curve":0.357,"c3":0.687,"c4":0.42},{"time":0.5,"x":10.05,"y":30.35,"curve":0.347,"c2":0.3,"c3":0.676,"c4":0.68},{"time":0.6,"x":1.1,"y":24.28},{"time":0.7,"x":2.41,"y":12.07},{"time":0.8}]},"toes_left":{"rotate":[{"angle":2.49},{"time":0.2,"angle":21.14},{"time":0.4,"angle":-5.13},{"time":0.5,"angle":24.75},{"time":0.8,"angle":2.49}]},"foot_left":{"rotate":[{"angle":-1.3},{"time":0.2,"angle":23},{"time":0.4,"angle":34.56},{"time":0.5,"angle":-5.93},{"time":0.8,"angle":-1.3}]},"shin_left":{"rotate":[{"angle":-81.6}]},"hip_left":{"rotate":[{"angle":11.31},{"time":0.4,"angle":0.8},{"time":0.6,"angle":-0.56},{"time":0.8,"angle":11.31}],"translate":[{},{"time":0.2,"x":28,"y":10.49},{"time":0.4,"x":5.68,"y":2.88},{"time":0.5,"x":17.26,"y":-5.93},{"time":0.7}]},"pelvis":{"rotate":[{},{"time":0.2,"angle":-5.75},{"time":0.6,"angle":-27.35},{"time":0.8}],"translate":[{},{"time":0.5,"x":6.08,"y":19.1},{"time":0.6,"x":6.29,"y":18.87},{"time":0.8}]},"palm_left":{"rotate":[{},{"time":0.6,"angle":21.74},{"time":0.8}]},"forearm_left":{"rotate":[{"angle":-16.54,"curve":0.234,"c2":0.27,"c3":0.75},{"time":0.2,"angle":-21.4,"curve":0.376,"c3":0.692,"c4":0.57},{"time":0.4,"angle":-9.61,"curve":0.255,"c2":0.33,"c3":0.75},{"time":0.6,"angle":38.21,"curve":0.523,"c2":0.01,"c3":0.761,"c4":0.67},{"time":0.8,"angle":-16.54}]},"shoulder_left":{"rotate":[{"angle":4.52,"curve":0.234,"c2":0.27,"c3":0.75},{"time":0.2,"angle":-29.79,"curve":0.376,"c3":0.692,"c4":0.57},{"time":0.4,"angle":-0.06,"curve":0.234,"c2":0.27,"c3":0.75},{"time":0.6,"angle":19.3,"curve":0.376,"c3":0.692,"c4":0.57},{"time":0.8,"angle":4.52}]},"body6":{"translate":[{},{"time":0.2,"x":3.46,"y":21.18},{"time":0.4,"x":-0.89,"y":-5.45},{"time":0.6,"x":-2.98,"y":-18.27},{"time":0.8}]},"palm_right":{"rotate":[{"angle":5.29},{"time":0.1,"angle":4.66},{"time":0.8,"angle":5.29}]},"forearm_right":{"rotate":[{"angle":-26.27,"curve":0.234,"c2":0.27,"c3":0.75},{"time":0.2,"angle":37.94,"curve":0.25,"c3":0.761,"c4":0.67},{"time":0.4,"angle":-19.06,"curve":0.255,"c2":0.33,"c3":0.75},{"time":0.6,"angle":8.24,"curve":0.376,"c3":0.692,"c4":0.57},{"time":0.8,"angle":-26.27}]},"shoulder_right":{"rotate":[{"angle":17.59,"curve":0.234,"c2":0.27,"c3":0.75},{"time":0.2,"angle":36.97,"curve":0.25,"c3":0.761,"c4":0.67},{"time":0.4,"angle":9.82,"curve":0.255,"c2":0.33,"c3":0.75},{"time":0.6,"angle":-26.93,"curve":0.376,"c3":0.692,"c4":0.57},{"time":0.8,"angle":17.59}]},"body5":{"translate":[{"x":3.08,"y":-12.23,"curve":0.234,"c2":0.27,"c3":0.75},{"time":0.2,"x":5.37,"y":-21.33,"curve":0.376,"c3":0.692,"c4":0.57},{"time":0.4,"x":-0.22,"y":0.86,"curve":0.234,"c2":0.27,"c3":0.75},{"time":0.6,"x":-2.13,"y":8.46,"curve":0.376,"c3":0.692,"c4":0.57},{"time":0.8,"x":3.08,"y":-12.23}]},"body4":{"rotate":[{"angle":-2.7},{"time":0.3,"angle":4.99},{"time":0.5,"angle":-1.97},{"time":0.7,"angle":3.02},{"time":0.8,"angle":-2.7}]},"body2":{"rotate":[{"angle":-14.36},{"time":0.1,"angle":-16.65},{"time":0.3,"angle":-18.01},{"time":0.5,"angle":-13.86},{"time":0.7,"angle":-18.38},{"time":0.8,"angle":-14.36}]},"Tom":{"translate":[{"x":0.1,"y":-83.27},{"time":0.1,"x":0.05,"y":-40.85},{"time":0.2,"x":0.03,"y":-21.94},{"time":0.3,"x":0.07,"y":-56.34},{"time":0.4,"x":0.1,"y":-83.27},{"time":0.6,"x":0.03,"y":-22.92},{"time":0.7,"x":0.06,"y":-49.27},{"time":0.8,"x":0.1,"y":-83.27}]},"Tom0":{"translate":[{"x":40,"y":60}]},"l_right":{"translate":[{"x":65.45,"y":27.39},{"time":0.1,"x":-181.9,"y":65.16},{"time":0.2,"x":-266.3,"y":284.59},{"time":0.3,"x":-256.3,"y":405.68},{"time":0.4,"x":-167.8,"y":265.22},{"time":0.5,"x":149.7,"y":256.69},{"time":0.6,"x":429.7,"y":255.64},{"time":0.7,"x":425.4,"y":56.48},{"time":0.8,"x":65.45,"y":27.39}]}}},"run_end":{"bones":{"l_left":{"translate":[{"curve":0.25,"c3":0.75},{"time":0.3333,"x":-42,"y":-6}]},"toes_right":{"rotate":[{"angle":-9.92},{"time":0.3333,"angle":2.69}]},"foor_right":{"rotate":[{"angle":-1.33},{"time":0.3333,"angle":-5.79}]},"shin_right":{"rotate":[{"angle":-77.49},{"time":0.3333,"angle":4.73}]},"hip_right":{"rotate":[{"angle":27.61},{"time":0.3333,"angle":3.15}],"translate":[{"x":-10.8,"y":7.23,"curve":0.357,"c3":0.687,"c4":0.42},{"time":0.3333}]},"toes_left":{"rotate":[{"angle":-5.13},{"time":0.3333,"angle":1.33}]},"foot_left":{"rotate":[{"angle":34.56},{"time":0.3333,"angle":3.85}]},"shin_left":{"rotate":[{"angle":-42.91},{"time":0.3333,"angle":7.99}]},"hip_left":{"rotate":[{"angle":14.99},{"time":0.3333,"angle":-10.01}],"translate":[{"x":5.68,"y":2.88},{"time":0.3333}]},"pelvis":{"rotate":[{"angle":-7.52},{"time":0.3333,"angle":-9.73}]},"forearm_left":{"rotate":[{"angle":-9.61,"curve":0.255,"c2":0.33,"c3":0.75},{"time":0.3333,"angle":-26.24}]},"shoulder_left":{"rotate":[{"angle":24.08,"curve":0.25,"c3":0.75},{"time":0.2667}]},"body6":{"translate":[{"x":-0.89,"y":-5.45},{"time":0.3333}]},"palm_right":{"rotate":[{"angle":2.22},{"time":0.3333}]},"forearm_right":{"rotate":[{"angle":-7.65,"curve":0.342,"c2":0.36,"c3":0.757},{"time":0.1667,"angle":-0.52,"curve":0.25,"c3":0.75},{"time":0.3333,"angle":-21.6}]},"shoulder_right":{"rotate":[{"angle":-3.46,"curve":0.375,"c2":0.62,"c3":0.716},{"time":0.0667,"angle":-9.5,"curve":0.25,"c3":0.75},{"time":0.3333,"angle":4.29}]},"body5":{"translate":[{"x":-0.22,"y":0.86,"curve":0.234,"c2":0.27,"c3":0.75},{"time":0.3333}]},"body4":{"rotate":[{"angle":-14,"curve":0.286,"c2":0.15,"c3":0.755},{"time":0.3333}]},"body2":{"rotate":[{"angle":-7.49,"curve":0.25,"c3":0.75},{"time":0.3333}]},"Tom":{"translate":[{"x":0.11,"y":-89.6},{"time":0.3333}]},"Tom0":{"rotate":[{"angle":4.63},{"time":0.3333}],"translate":[{"x":16.67,"y":25},{"time":0.3333}]},"l_right":{"translate":[{"x":-117.45,"y":203.56,"curve":0.375,"c2":0.5,"c3":0.75},{"time":0.1333,"x":21.39,"y":1.45}]}}},"run_start":{"slots":{"shoulder_right":{"attachment":[{"time":0.4,"name":null}]}},"bones":{"l_left":{"translate":[{"x":-42,"y":-6},{"time":0.2667,"x":-239.23,"y":62.66},{"time":0.4,"x":-153.69,"y":224.75}]},"toes_right":{"rotate":[{"angle":2.69,"curve":"stepped"},{"time":0.1333,"angle":2.69},{"time":0.4,"angle":13.25}]},"foor_right":{"rotate":[{"angle":-5.79},{"time":0.1333,"angle":5.95},{"time":0.2667,"angle":12.56},{"time":0.4,"angle":-1.13}]},"shin_right":{"rotate":[{"angle":4.73,"curve":"stepped"},{"time":0.1333,"angle":4.73},{"time":0.4,"angle":-6.09}]},"hip_right":{"rotate":[{"angle":3.15,"curve":"stepped"},{"time":0.1333,"angle":3.15},{"time":0.4,"angle":2.92}]},"toes_left":{"rotate":[{"angle":1.33,"curve":"stepped"},{"time":0.1333,"angle":1.33},{"time":0.4,"angle":2.49}]},"foot_left":{"rotate":[{"angle":3.85},{"time":0.1333,"angle":15.71},{"time":0.4,"angle":-1.3}]},"shin_left":{"rotate":[{"angle":7.99,"curve":"stepped"},{"time":0.1333,"angle":7.99},{"time":0.4,"angle":-1.89}]},"hip_left":{"rotate":[{"angle":-10.01,"curve":"stepped"},{"time":0.1333,"angle":-10.01},{"time":0.4,"angle":0.8}]},"pelvis":{"rotate":[{"angle":-9.73,"curve":"stepped"},{"time":0.1333,"angle":-9.73},{"time":0.4}]},"forearm_left":{"rotate":[{"angle":-26.24,"curve":0.25,"c3":0.75},{"time":0.2667,"angle":-8.3},{"time":0.4,"angle":-16.54}]},"shoulder_left":{"rotate":[{"curve":0.25,"c3":0.75},{"time":0.2667,"angle":19.25},{"time":0.4,"angle":4.52}]},"palm_right":{"rotate":[{"time":0.1333},{"time":0.4,"angle":5.29}]},"forearm_right":{"rotate":[{"angle":-21.6,"curve":"stepped"},{"time":0.1333,"angle":-21.6},{"time":0.4,"angle":-26.27}]},"shoulder_right":{"rotate":[{"angle":4.29,"curve":0.25,"c3":0.75},{"time":0.2333,"angle":-1.3},{"time":0.4,"angle":17.59}]},"body5":{"translate":[{"time":0.1333},{"time":0.4,"x":3.08,"y":-12.23}]},"body4":{"rotate":[{},{"time":0.2667,"angle":-12.39},{"time":0.4,"angle":-2.7}]},"body2":{"rotate":[{},{"time":0.1333,"angle":-16},{"time":0.4,"angle":-14.36}]},"Tom":{"translate":[{},{"time":0.1333,"x":0.03,"y":-25.55},{"time":0.2667,"x":0.12,"y":-99.99},{"time":0.4,"x":0.1,"y":-83.27}]},"Tom0":{"translate":[{"time":0.1333},{"time":0.4,"x":40,"y":60}]},"l_right":{"translate":[{"x":21.39,"y":1.45,"curve":"stepped"},{"time":0.1333,"x":21.39,"y":1.45},{"time":0.4,"x":65.45,"y":27.39}]}}}}}